Workbook

Sheet Summary
A1: Headline metric | B1: As-Is value | C1: Unit | D1: How it is calculated
A2: TIME
A3: Expected turnaround time (TAT) | B3: =('Activity times'!K29+'Activity times'!J29/60)/24 -> 11.496354 | C3: days | D3: (all expected waits + all expected touch time) ÷ 24; includes rework and exceptions
A4: Happy-path TAT (nothing goes wrong) | B4: =(SUMIF('Activity times'!F2:F28,"Main",'Activity times'!I2:I28)+SUMIF('Activity times'!F2:F28,"Main",'Activity times'!H2:H28)/60)/24 -> 9.7083333 | C4: days | D4: Main-path rows only
A5: Expected touch time (anyone working on it) | B5: ='Activity times'!J29/60 -> 6.3125 | C5: hours | D5: Sum of expected touch minutes ÷ 60
A6: Expected staff touch time | B6: =SUMIF('Activity times'!E2:E28,"Staff",'Activity times'!J2:J28)/60 -> 5.8125 | C6: hours | D6: Touch time of bank staff only (excludes the customer's own time)
A7: Process efficiency | B7: =B5/(B3*24) -> 0.02287863 | C7: % | D7: Touch time ÷ TAT: the share of elapsed time in which someone is actually working
A8: Share of time spent waiting | B8: =1-B7 -> 0.97712137 | C8: % | D8: 1 − process efficiency
A9: Expected document-chase time | B9: ='Activity times'!K9 -> 36 | C9: hours | D9: A8 expected wait (share × one round)
A10: Share of TAT caused by the document chase | B10: =B9/(B3*24) -> 0.13047615 | C10: % | D10: A8 expected wait ÷ TAT
A11: Staff hours per month | B11: =B6*Inputs!$C$8 -> 11625 | C11: hours | D11: Expected staff touch × applications per month (AS-01)
A12: HANDOFFS AND RE-KEYING
A13: Handoffs on the main (happy) path | B13: =COUNTIF(Handoffs!C2:C18,"Main") -> 10 | C13: count | D13: Rows in Handoffs with Path = Main
A14: Handoffs added by one document-chase round | B14: =COUNTIF(Handoffs!C2:C18,"Rework") -> 4 | C14: count | D14: Added every time A8 repeats
A15: Handoffs on exception paths | B15: =COUNTIF(Handoffs!C2:C18,"Exception") -> 3 | C15: count | D15: Fraud referral and deviation approval
A16: Re-keying points (all paths) | B16: =COUNTIF(Handoffs!H2:H18,"Yes") -> 5 | C16: count | D16: Handoffs where data is typed again
A17: Systems in the process | B17: =COUNTA(Systems!A2:A6) -> 5 | C17: count | D17: Formal systems (email and spreadsheets excluded)
A18: Manual bridges between systems | B18: =COUNTIF(Systems!E2:E6,"*manual bridge*") -> 4 | C18: count | D18: Systems where data is moved by hand
A19: BENCHMARKS (from sources)
A20: Kotak: typical approval time | B20: 24–72 | C20: hours | D20: S05 (approval only, not disbursal)
A21: ICICI: approval after complete documents | B21: 48 | C21: hours | D21: S03 — note the condition: complete documentation
A22: Newgen case study: TAT after digital LOS | B22: 48 | C22: hours | D22: S09 (vendor claim, MSME lending)
A24: All figures are estimates built from the assumptions in the Inputs sheet (details in assumption_register.xlsx). The conclusions rely on relative sizes (which stage waits longest, how much time is waiting) rather than on exact numbers.
A25: Reconstruction from public sources per 07_source_log; no Meridian Bank data was available.

Sheet Comparison
A1: Metric | B1: As-Is | C1: To-Be | D1: Change | E1: Unit
A2: TIME
A3: Expected turnaround time (TAT) | B3: =Summary!B3 -> 11.496354 | C3: =('To-Be times'!K19+'To-Be times'!J19/60)/24 -> 1.7659722 | D3: =IF(B3=0,"—",(C3-B3)/B3) -> -0.8463885 | E3: days
A4: Happy-path turnaround time | B4: =Summary!B4 -> 9.7083333 | C4: =(SUMIF('To-Be times'!F2:F18,"Main",'To-Be times'!I2:I18)+SUMIF('To-Be times'!F2:F18,"Main",'To-Be times'!H2:H18)/60)/24 -> 1.45625 | D4: =IF(B4=0,"—",(C4-B4)/B4) -> -0.85 | E4: days
A5: Expected touch time (anyone working on it) | B5: =Summary!B5 -> 6.3125 | C5: ='To-Be times'!J19/60 -> 1.1833333 | D5: =IF(B5=0,"—",(C5-B5)/B5) -> -0.81254125 | E5: hours
A6: Expected staff touch time | B6: =Summary!B6 -> 5.8125 | C6: =SUMIF('To-Be times'!E2:E18,"Staff",'To-Be times'!J2:J18)/60 -> 0.46666667 | D6: =IF(B6=0,"—",(C6-B6)/B6) -> -0.91971326 | E6: hours
A7: Process efficiency (touch ÷ TAT) | B7: =Summary!B7 -> 0.02287863 | C7: =C5/(C3*24) -> 0.02791978 | D7: =IF(B7=0,"—",(C7-B7)/B7) -> 0.22034317 | E7: %
A8: Staff hours per month (AS-01 volume) | B8: =Summary!B11 -> 11625 | C8: =C6*Inputs!$C$8 -> 933.33333 | D8: =IF(B8=0,"—",(C8-B8)/B8) -> -0.91971326 | E8: hours
A9: HANDOFFS, RE-KEYING, REWORK
A10: Handoffs on the main path | B10: =Summary!B13 -> 10 | C10: =COUNTIF('To-Be handoffs'!C2:C14,"Main") -> 6 | D10: =IF(B10=0,"—",(C10-B10)/B10) -> -0.4 | E10: count
A11: Handoffs added by one rework round | B11: =Summary!B14 -> 4 | C11: =COUNTIF('To-Be handoffs'!C2:C14,"Rework") -> 2 | D11: =IF(B11=0,"—",(C11-B11)/B11) -> -0.5 | E11: count
A12: Re-keying points | B12: =Summary!B16 -> 5 | C12: =COUNTIF('To-Be handoffs'!H2:H14,"Yes") -> 0 | D12: =IF(B12=0,"—",(C12-B12)/B12) -> -1 | E12: count
A13: Expected rework rounds per application | B13: =Inputs!$C$2*Inputs!$C$3 -> 0.5 | C13: =Inputs!$C$9 -> 0.1 | D13: =IF(B13=0,"—",(C13-B13)/B13) -> -0.8 | E13: rounds
A14: Manual bridges between systems | B14: =Summary!B18 -> 4 | C14: 0 | D14: =IF(B14=0,"—",(C14-B14)/B14) -> -1 | E14: count
A15: Manual staff tasks on the happy path | B15: =COUNTIFS('Activity times'!F2:F28,"Main",'Activity times'!E2:E28,"Staff") -> 22 | C15: =COUNTIFS('To-Be times'!F2:F18,"Main",'To-Be times'!E2:E18,"Staff") -> 2 | D15: =IF(B15=0,"—",(C15-B15)/B15) -> -0.90909091 | E15: count
A17: Headline
A18: ="Turnaround from "&TEXT(B3,"0.0")&" to "&TEXT(C3,"0.0")&" days ("&TEXT(-D3,"0%")&" faster); handoffs from "&B10&" to "&C10&"; re-keying from "&B12&" to "&C12&"." -> Turnaround from 11.5 to 1.8 days (85% faster); handoffs from 10 to 6; re-keying from 5 to 0.
A20: To-Be handoffs and re-keying are recounted on the To-Be handoffs sheet from loan_origination_to_be.drawio.
A21: Manual bridges fall to 0 only if the integrations in the requirements (FR-02, FR-09 to FR-11, FR-24) are built (blue = design assumption).
A22: Process efficiency barely changes: staff work falls sharply, but most of the remaining To-Be time is the customer's own time to accept and e-sign, which the bank cannot remove.
A23: Both columns are estimates made the same way, so the comparison is like for like.

Sheet Inputs
A1: Assumption ID | B1: Input | C1: Value | D1: Unit
A2: AS-02 | B2: Share of files incomplete at the first completeness check (A7) | C2: 0.4 | D2: share
A3: AS-03 | B3: Average document-chase rounds per incomplete file | C3: 1.25 | D3: rounds
A4: AS-04 | B4: Elapsed time of one document-chase round | C4: 72 | D4: hours
A5: AS-05 | B5: Staff touch time of one document-chase round | C5: 30 | D5: minutes
A6: AS-06 | B6: Share of applications with a screening hit | C6: 0.05 | D6: share
A7: AS-08 | B7: Share of applications needing a deviation approval | C7: 0.15 | D7: share
A8: AS-01 | B8: Applications per month (capacity figures only) | C8: 2000 | D8: applications
A9: AS-20 | B9: To-Be: share of submissions with a missing or unreadable item | C9: 0.1 | D9: share
A10: AS-22 | B10: To-Be: share of automated checks needing manual resolution | C10: 0.1 | D10: share
A11: AS-23 | B11: To-Be: share of applications referred to an underwriter | C11: 0.35 | D11: share
A13: Blue values on yellow are inputs: change them here and every sheet recalculates. Each value, its reasoning and confidence are recorded in assumption_register.xlsx.

Sheet Activity times
A1: ID | B1: Activity | C1: Stage | D1: Lane (who does it) | E1: Actor type | F1: Path | G1: Share of applications | H1: Touch time (min) | I1: Wait before it starts (h) | J1: Expected touch (min) | K1: Expected wait (h) | L1: Source / assumption ID
A2: A1 | B2: Submit loan application | C2: Capture | D2: Customer | E2: Customer | F2: Main | G2: 1 | H2: 20 | I2: 0 | J2: =G2*H2 -> 20 | K2: =G2*I2 -> 0 | L2: AS-17
A3: A2 | B3: Capture application in LOS | C3: Capture | D3: Branch / Sales | E3: Staff | F3: Main | G3: 1 | H3: 20 | I3: 0 | J3: =G3*H3 -> 20 | K3: =G3*I3 -> 0 | L3: AS-17, AS-29 · Handoff H1
A4: A3 | B4: Collect KYC documents | C4: Capture | D4: Branch / Sales | E4: Staff | F4: Main | G4: 1 | H4: 15 | I4: 0 | J4: =G4*H4 -> 15 | K4: =G4*I4 -> 0 | L4: AS-17
A5: A4 | B5: Collect income documents | C5: Capture | D5: Branch / Sales | E5: Staff | F5: Main | G5: 1 | H5: 15 | I5: 0 | J5: =G5*H5 -> 15 | K5: =G5*I5 -> 0 | L5: AS-17
A6: A5 | B6: Obtain customer consents | C6: Capture | D6: Branch / Sales | E6: Staff | F6: Main | G6: 1 | H6: 5 | I6: 0 | J6: =G6*H6 -> 5 | K6: =G6*I6 -> 0 | L6: AS-17
A7: A6 | B7: Scan and hand over file | C7: Capture | D7: Branch / Sales | E7: Staff | F7: Main | G7: 1 | H7: 15 | I7: 0 | J7: =G7*H7 -> 15 | K7: =G7*I7 -> 0 | L7: AS-17, AS-30
A8: A7 | B8: Check document completeness | C8: Verify | D8: Credit Operations | E8: Staff | F8: Main | G8: 1 | H8: 15 | I8: 24 | J8: =G8*H8 -> 15 | K8: =G8*I8 -> 24 | L8: AS-10 · Handoff H2
A9: A8 | B9: Request missing documents (one round) | C9: Verify | D9: Branch / Credit Ops / Customer | E9: Staff | F9: Rework | G9: =Inputs!$C$2*Inputs!$C$3 -> 0.5 | H9: =Inputs!$C$5 -> 30 | I9: =Inputs!$C$4 -> 72 | J9: =G9*H9 -> 15 | K9: =G9*I9 -> 36 | L9: AS-02, AS-03, AS-04, AS-05 · Handoffs H3–H6
A10: A9 | B10: Verify KYC | C10: Verify | D10: Credit Operations | E10: Staff | F10: Main | G10: 1 | H10: 15 | I10: 4 | J10: =G10*H10 -> 15 | K10: =G10*I10 -> 4 | L10: AS-16, AS-17
A11: A10 | B11: Validate PAN and identity | C11: Verify | D11: Credit Operations | E11: Staff | F11: Main | G11: 1 | H11: 10 | I11: 1 | J11: =G11*H11 -> 10 | K11: =G11*I11 -> 1 | L11: AS-16, AS-17, AS-31
A12: A11 | B12: Cross-check application data | C12: Verify | D12: Credit Operations | E12: Staff | F12: Main | G12: 1 | H12: 20 | I12: 2 | J12: =G12*H12 -> 20 | K12: =G12*I12 -> 2 | L12: AS-16, AS-17
A13: A12 | B13: Verify employment | C13: Verify | D13: Credit Operations | E13: Staff | F13: Main | G13: 1 | H13: 15 | I13: 36 | J13: =G13*H13 -> 15 | K13: =G13*I13 -> 36 | L13: AS-11, AS-32 · Handoff H7
A14: A13 | B14: Screen fraud and negative lists | C14: Verify | D14: Credit Operations | E14: Staff | F14: Main | G14: 1 | H14: 10 | I14: 2 | J14: =G14*H14 -> 10 | K14: =G14*I14 -> 2 | L14: AS-16, AS-17
A15: A13R | B15: Review screening hit | C15: Verify | D15: Risk & Compliance | E15: Staff | F15: Exception | G15: =Inputs!$C$6 -> 0.05 | H15: 15 | I15: 24 | J15: =G15*H15 -> 0.75 | K15: =G15*I15 -> 1.2 | L15: AS-06, AS-07 · Handoff H8
A16: A14 | B16: Pull credit bureau report | C16: Assess | D16: Credit Operations | E16: Staff | F16: Main | G16: 1 | H16: 5 | I16: 1 | J16: =G16*H16 -> 5 | K16: =G16*I16 -> 1 | L16: AS-16, AS-17
A17: A15 | B17: Assess income and obligations | C17: Assess | D17: Underwriting | E17: Staff | F17: Main | G17: 1 | H17: 30 | I17: 24 | J17: =G17*H17 -> 30 | K17: =G17*I17 -> 24 | L17: AS-12, AS-28 · Handoff H9
A18: A16 | B18: Calculate debt-to-income ratio | C18: Assess | D18: Underwriting | E18: Staff | F18: Main | G18: 1 | H18: 15 | I18: 0 | J18: =G18*H18 -> 15 | K18: =G18*I18 -> 0 | L18: AS-28
A19: A17 | B19: Apply credit policy checks | C19: Assess | D19: Underwriting | E19: Staff | F19: Main | G19: 1 | H19: 15 | I19: 1 | J19: =G19*H19 -> 15 | K19: =G19*I19 -> 1 | L19: AS-16, AS-28, AS-33
A20: A18 | B20: Refer deviation for approval | C20: Decide | D20: Credit Manager | E20: Staff | F20: Exception | G20: =Inputs!$C$7 -> 0.15 | H20: 20 | I20: 36 | J20: =G20*H20 -> 3 | K20: =G20*I20 -> 5.4 | L20: AS-08, AS-09, AS-34 · Handoffs H10–H11
A21: A19 | B21: Record credit decision | C21: Decide | D21: Underwriting | E21: Staff | F21: Main | G21: 1 | H21: 10 | I21: 2 | J21: =G21*H21 -> 10 | K21: =G21*I21 -> 2 | L21: AS-16, AS-28
A22: A20 | B22: Issue sanction letter and KFS | C22: Close | D22: Disbursement | E22: Staff | F22: Main | G22: 1 | H22: 20 | I22: 8 | J22: =G22*H22 -> 20 | K22: =G22*I22 -> 8 | L22: AS-16, AS-17 · Handoff H12
A23: A21 | B23: Accept sanction | C23: Close | D23: Customer | E23: Customer | F23: Main | G23: 1 | H23: 10 | I23: 36 | J23: =G23*H23 -> 10 | K23: =G23*I23 -> 36 | L23: AS-13, AS-17 · Handoff H13
A24: A22 | B24: Execute loan agreement | C24: Close | D24: Disbursement / Branch / Customer | E24: Staff | F24: Main | G24: 1 | H24: 20 | I24: 24 | J24: =G24*H24 -> 20 | K24: =G24*I24 -> 24 | L24: AS-14, AS-17 · Handoff H14
A25: A23 | B25: Register repayment mandate | C25: Close | D25: Disbursement | E25: Staff | F25: Main | G25: 1 | H25: 15 | I25: 48 | J25: =G25*H25 -> 15 | K25: =G25*I25 -> 48 | L25: AS-15, AS-17, AS-35
A26: A24 | B26: Perform final compliance check | C26: Close | D26: Risk & Compliance | E26: Staff | F26: Main | G26: 1 | H26: 20 | I26: 8 | J26: =G26*H26 -> 20 | K26: =G26*I26 -> 8 | L26: AS-16, AS-17 · Handoff H15
A27: A25 | B27: Disburse funds | C27: Close | D27: Disbursement | E27: Staff | F27: Main | G27: 1 | H27: 15 | I27: 4 | J27: =G27*H27 -> 15 | K27: =G27*I27 -> 4 | L27: AS-16, AS-17 · Handoff H16
A28: A26 | B28: Send welcome pack and archive file | C28: Close | D28: Disbursement | E28: Staff | F28: Main | G28: 1 | H28: 10 | I28: 2 | J28: =G28*H28 -> 10 | K28: =G28*I28 -> 2 | L28: AS-16, AS-17 · Handoff H17
B29: Total (expected per application) | J29: =SUM(J2:J28) -> 378.75 | K29: =SUM(K2:K28) -> 269.6
A31: Share of applications: 1 = every approved application passes through it. Rework and exception rows are weighted by how often they happen, so totals are the expected time for a typical approved application.
A32: Blue = input estimate · green = linked from the Inputs sheet · black = formula. Wait = elapsed hours before the activity starts (queues, customer response, handoffs), counted in calendar hours (AS-18).

Sheet Bottleneck
A1: Stage | B1: Expected wait (h) | C1: Share of all waiting | D1: Expected touch (min) | E1: Biggest single wait in the stage
A2: Capture | B2: =SUMIF('Activity times'!C2:C28,A2,'Activity times'!K2:K28) -> 0 | C2: =B2/SUM($B$2:$B$6) -> 0 | D2: =SUMIF('Activity times'!C2:C28,A2,'Activity times'!J2:J28) -> 90 | E2: —
A3: Verify | B3: =SUMIF('Activity times'!C2:C28,A3,'Activity times'!K2:K28) -> 106.2 | C3: =B3/SUM($B$2:$B$6) -> 0.39391691 | D3: =SUMIF('Activity times'!C2:C28,A3,'Activity times'!J2:J28) -> 100.75 | E3: A8 document chase (72 h per round) and A12 employer reply (36 h)
A4: Assess | B4: =SUMIF('Activity times'!C2:C28,A4,'Activity times'!K2:K28) -> 26 | C4: =B4/SUM($B$2:$B$6) -> 0.096439169 | D4: =SUMIF('Activity times'!C2:C28,A4,'Activity times'!J2:J28) -> 65 | E4: A15 underwriting queue (24 h)
A5: Decide | B5: =SUMIF('Activity times'!C2:C28,A5,'Activity times'!K2:K28) -> 7.4 | C5: =B5/SUM($B$2:$B$6) -> 0.027448071 | D5: =SUMIF('Activity times'!C2:C28,A5,'Activity times'!J2:J28) -> 13 | E5: A18 deviation approval (36 h, 15% of cases)
A6: Close | B6: =SUMIF('Activity times'!C2:C28,A6,'Activity times'!K2:K28) -> 130 | C6: =B6/SUM($B$2:$B$6) -> 0.48219585 | D6: =SUMIF('Activity times'!C2:C28,A6,'Activity times'!J2:J28) -> 110 | E6: A23 mandate registration (48 h), A21 customer acceptance (36 h), A22 branch visit (24 h)
A7: Total | B7: =SUM(B2:B6) -> 269.6 | D7: =SUM(D2:D6) -> 378.75
A9: Bottleneck stage (most waiting): | C9: =INDEX(A2:A6,MATCH(MAX(B2:B6),B2:B6,0)) -> Close | D9: =MAX(B2:B6) -> 130 | E9: =TEXT(MAX(B2:B6)/SUM(B2:B6),"0%")&" of all waiting" -> 48% of all waiting
A10: Second-largest: | C10: =INDEX(A2:A6,MATCH(LARGE(B2:B6,2),B2:B6,0)) -> Verify | D10: =LARGE(B2:B6,2) -> 106.2 | E10: =TEXT(LARGE(B2:B6,2)/SUM(B2:B6),"0%")&" of all waiting" -> 39% of all waiting

Sheet To-Be times
A1: ID | B1: Activity | C1: Stage | D1: Lane (who does it) | E1: Actor type | F1: Path | G1: Share of applications | H1: Touch time (min) | I1: Wait before it starts (h) | J1: Expected touch (min) | K1: Expected wait (h) | L1: Source / assumption ID
A2: N1 | B2: Apply online and upload documents (replaces A1–A5) | C2: Capture | D2: Customer | E2: Customer | F2: Main | G2: 1 | H2: 25 | I2: 0 | J2: =G2*H2 -> 25 | K2: =G2*I2 -> 0 | L2: AS-26
A3: N2 | B3: Validate completeness and document quality (automatic) | C3: Capture | D3: LOS (system) | E3: System | F3: Main | G3: 1 | H3: 0 | I3: 0 | J3: =G3*H3 -> 0 | K3: =G3*I3 -> 0 | L3: Design
A4: N3 | B4: Missing-item round via upload link (rework) | C4: Capture | D4: Customer | E4: Customer | F4: Rework | G4: =Inputs!$C$9 -> 0.1 | H4: 10 | I4: 24 | J4: =G4*H4 -> 1 | K4: =G4*I4 -> 2.4 | L4: AS-20, AS-21
A5: N4 | B5: Run e-KYC, PAN, bureau and employment checks (replaces A9, A10, A12, A14) | C5: Verify | D5: LOS (system) | E5: System | F5: Main | G5: 1 | H5: 0 | I5: 0 | J5: =G5*H5 -> 0 | K5: =G5*I5 -> 0 | L5: Design
A6: N4X | B6: Resolve verification exception | C6: Verify | D6: Credit Operations | E6: Staff | F6: Exception | G6: =Inputs!$C$10 -> 0.1 | H6: 30 | I6: 4 | J6: =G6*H6 -> 3 | K6: =G6*I6 -> 0.4 | L6: AS-22
A7: N5 | B7: Screen fraud and negative lists (automatic, A13) | C7: Verify | D7: LOS (system) | E7: System | F7: Main | G7: 1 | H7: 0 | I7: 0 | J7: =G7*H7 -> 0 | K7: =G7*I7 -> 0 | L7: Design
A8: A13R | B8: Review screening hit (LOS queue with SLA) | C8: Verify | D8: Risk & Compliance | E8: Staff | F8: Exception | G8: =Inputs!$C$6 -> 0.05 | H8: 15 | I8: 8 | J8: =G8*H8 -> 0.75 | K8: =G8*I8 -> 0.4 | L8: AS-06, AS-25
A9: N7 | B9: Calculate DTI and apply policy rules (automatic, A16–A17) | C9: Assess | D9: LOS (system) | E9: System | F9: Main | G9: 1 | H9: 0 | I9: 0 | J9: =G9*H9 -> 0 | K9: =G9*I9 -> 0 | L9: Design
A10: A15 | B10: Review referred application | C10: Assess | D10: Underwriting | E10: Staff | F10: Exception | G10: =Inputs!$C$11 -> 0.35 | H10: 20 | I10: 8 | J10: =G10*H10 -> 7 | K10: =G10*I10 -> 2.8 | L10: AS-23
A11: A18 | B11: Approve deviation in LOS (SLA) | C11: Decide | D11: Credit Manager | E11: Staff | F11: Exception | G11: =Inputs!$C$7 -> 0.15 | H11: 15 | I11: 8 | J11: =G11*H11 -> 2.25 | K11: =G11*I11 -> 1.2 | L11: AS-08, AS-24
A12: A19 | B12: Record credit decision (automatic or by underwriter) | C12: Decide | D12: LOS / Underwriting | E12: System | F12: Main | G12: 1 | H12: 2 | I12: 0 | J12: =G12*H12 -> 2 | K12: =G12*I12 -> 0 | L12: Design
A13: N9 | B13: Issue offer with KFS digitally (A20) | C13: Close | D13: LOS (system) | E13: System | F13: Main | G13: 1 | H13: 0 | I13: 0 | J13: =G13*H13 -> 0 | K13: =G13*I13 -> 0 | L13: Design
A14: N6 | B14: Accept offer, e-sign agreement, set up e-mandate (replaces A21–A23) | C14: Close | D14: Customer | E14: Customer | F14: Main | G14: 1 | H14: 15 | I14: 24 | J14: =G14*H14 -> 15 | K14: =G14*I14 -> 24 | L14: AS-26
A15: N6R | B15: Confirm e-mandate registration | C15: Close | D15: LOS (system) | E15: System | F15: Main | G15: 1 | H15: 0 | I15: 4 | J15: =G15*H15 -> 0 | K15: =G15*I15 -> 4 | L15: AS-26
A16: A24 | B16: Final compliance check (evidence compiled automatically) | C16: Close | D16: Risk & Compliance | E16: Staff | F16: Main | G16: 1 | H16: 10 | I16: 4 | J16: =G16*H16 -> 10 | K16: =G16*I16 -> 4 | L16: AS-27
A17: A25 | B17: Disburse funds (loan account created via LOS–CBS link) | C17: Close | D17: Disbursement | E17: Staff | F17: Main | G17: 1 | H17: 5 | I17: 2 | J17: =G17*H17 -> 5 | K17: =G17*I17 -> 2 | L17: AS-27
A18: A26 | B18: Send welcome pack and archive file (automatic) | C18: Close | D18: LOS (system) | E18: System | F18: Main | G18: 1 | H18: 0 | I18: 0 | J18: =G18*H18 -> 0 | K18: =G18*I18 -> 0 | L18: Design
B19: Total (expected per application) | J19: =SUM(J2:J18) -> 71 | K19: =SUM(K2:K18) -> 41.2
A21: To-Be estimates for the redesigned process (loan_origination_to_be.drawio). 'System' rows are automatic steps with no staff touch time.
A22: Blue = input estimate · green = linked from the Inputs sheet · black = formula. Wait = elapsed hours before the activity starts (queues, customer response, handoffs), counted in calendar hours (AS-18).

Sheet To-Be handoffs
A1: ID | B1: Activity | C1: Path | D1: From | E1: To | F1: Object handed over | G1: Mechanism | H1: Is data re-keyed? | I1: Compared with As-Is
A2: TH1 | B2: N1 → N2 | C2: Main | D2: Customer | E2: Loan system | F2: Application, documents, e-consent | G2: Digital form and upload | H2: No | I2: Replaces H1 (paper form re-typed) and H2 (branch → Credit Ops)
A3: TH2 | B3: N9 → N6 | C3: Main | D3: Loan system | E3: Customer | F3: Offer and Key Fact Statement | G3: App / email | H3: No | I3: Replaces H12 (re-keyed into sanction letter) and H13
A4: TH3 | B4: N6 → N6R | C4: Main | D4: Customer | E4: Loan system | F4: Acceptance, e-signed agreement, e-mandate | G4: App (Aadhaar OTP e-sign) | H4: No | I4: Replaces H14 (branch visit to sign)
A5: TH4 | B5: N6R → A24 | C5: Main | D5: Loan system | E5: Risk & Compliance | F5: File with evidence checklist | G5: LOS queue | H5: No | I5: Replaces H15
A6: TH5 | B6: A24 → A25 | C6: Main | D6: Risk & Compliance | E6: Disbursement | F6: File cleared for disbursal | G6: LOS status | H6: No | I6: Replaces H16 (re-keyed into core banking)
A7: TH6 | B7: A26 | C7: Main | D7: Loan system | E7: Customer | F7: Funds and welcome pack | G7: CBS credit + email | H7: No | I7: Replaces H17
A8: TH7 | B8: N3 | C8: Rework | D8: Loan system | E8: Customer | F8: One list of all missing items | G8: SMS / email with upload link | H8: No | I8: Replaces H3 and H4 (email to branch, call to customer)
A9: TH8 | B9: N3 → N2 | C9: Rework | D9: Customer | E9: Loan system | F9: Missing item | G9: Upload link | H9: No | I9: Replaces H5 and H6 (branch visit, re-scan)
A10: TH9 | B10: N4 → N4X | C10: Exception | D10: Loan system | E10: Credit Operations | F10: Failed automated check | G10: LOS exception queue | H10: No | I10: New: staff see only failures
A11: TH10 | B11: N5 → A13R | C11: Exception | D11: Loan system | E11: Risk & Compliance | F11: Screening hit | G11: LOS queue with SLA | H11: No | I11: Replaces H8 (email)
A12: TH11 | B12: N7 → A15 | C12: Exception | D12: Loan system | E12: Underwriting | F12: Referred application with reasons | G12: LOS queue | H12: No | I12: Replaces H9 for referred cases only
... A14: TH13 | B14: A18 → A19 | C14: Exception | D14: Credit Manager | E14: Loan system | F14: Deviation decision | G14: Recorded in LOS | H14: No | I14: Replaces H11 (email)
A16: Counted from loan_origination_to_be.drawio in the same way as the As-Is Handoffs sheet: a handoff is any point where work passes to a different person, team, system or pool. Automatic steps inside the loan system are not counted as handoffs.

Sheet Handoffs
A1: ID | B1: Activity | C1: Path | D1: From actor | E1: To actor | F1: Object handed over | G1: Mechanism | H1: Is data re-keyed? | I1: Wait introduced | J1: Failure mode | K1: Source
A2: H1 | B2: A1 → A2 | C2: Main | D2: Customer | E2: Branch Sales Officer | F2: Signed application form | G2: Paper form at branch (or web form) | H2: Yes | I2: Same day (estimate) | J2: Form details typed into the LOS by hand; typing errors in name, PAN or DOB cause KYC and bureau mismatches later | K2: S06; Assumption
A3: H2 | B3: A6 → A7 | C3: Main | D3: Branch Sales Officer | E3: Credit Operations Analyst | F3: Application file with scanned documents | G3: DMS scan + LOS queue (originals sometimes couriered) | H3: No | I3: Up to 1 working day, plus time in the Credit Ops queue (estimate) | J3: File held at branch until batch sent; documents scanned under the wrong type or application; poor scan quality | K3: Assumption
A4: H3 | B4: A7 → A8 | C4: Rework | D4: Credit Operations Analyst | E4: Branch Sales Officer | F4: List of missing / defective documents | G4: Email | H4: No | I4: Hours to 1 working day (estimate) | J4: Request not picked up promptly at the branch; list only covers the first problem found | K4: S03, S05; Assumption
A5: H4 | B5: A8 | C5: Rework | D5: Branch Sales Officer | E5: Customer | F5: Request for missing documents | G5: Phone / SMS | H5: No | I5: Several days waiting for the customer (estimate) | J5: Request passed on verbally and the wrong document is collected; customer unreachable or gives up | K5: Assumption
A6: H5 | B6: A8 | C6: Rework | D6: Customer | E6: Branch Sales Officer | F6: Missing documents | G6: Branch visit, email or WhatsApp | H6: No | I6: Several days (estimate) | J6: Document still wrong or unreadable; customer withdraws | K6: Assumption
A7: H6 | B7: A8 → A7 | C7: Rework | D7: Branch Sales Officer | E7: Credit Operations Analyst | F7: Updated application file | G7: DMS upload + LOS queue | H7: No | I7: Back of the Credit Ops queue again (estimate) | J7: File waits in the queue a second time; loop can repeat | K7: Assumption
A8: H7 | B8: A12 | C8: Main | D8: Credit Operations Analyst | E8: Employer HR (external) | F8: Employment verification request | G8: Email / phone | H8: No | I8: 1–3 working days (estimate) | J8: Employer does not respond; small employers hard to verify; result kept only in email | K8: S07; Assumption
A9: H8 | B9: A13 | C9: Exception | D9: Credit Operations Analyst | E9: Risk & Compliance Officer | F9: Fraud / negative-list screening hit | G9: Email | H9: No | I9: 1 working day (estimate) | J9: False positives hold up genuine applications; referral not tracked in the LOS | K9: S08, S01
A10: H9 | B10: A14 → A15 | C10: Main | D10: Credit Operations Analyst | E10: Underwriter | F10: Verified file with bureau report | G10: LOS queue | H10: Yes | I10: Time in the underwriting queue (estimate) | J10: Underwriter copies income and obligation figures into a spreadsheet; income checked a second time | K10: S06, S02
A11: H10 | B11: A18 | C11: Exception | D11: Underwriter | E11: Credit Manager | F11: Deviation case for approval | G11: Email | H11: Yes | I11: 1–2 working days (estimate) | J11: Case summary retyped into email; approver unavailable; status not visible in the LOS | K11: S08; Assumption
A12: H11 | B12: A18 → A19 | C12: Exception | D12: Credit Manager | E12: Underwriter | F12: Deviation decision | G12: Email | H12: No | I12: Hours (estimate) | J12: Decision recorded only in email, not in the LOS | K12: Assumption
... A18: H17 | B18: A25 → A26 | C18: Main | D18: Disbursement Officer | E18: Customer | F18: Funds credited and welcome pack | G18: CBS credit + email/post | H18: No | I18: Same day | J18: Signed documents not sent to the customer; welcome pack delayed | K18: S02, S07
A20: Path: Main = happy path every approved application follows; Rework = the document-chase loop (A8), which can repeat; Exception = only for some applications.
A21: All waits are estimates, to be recorded in 00_assumption_register. Reconstruction from public sources per 07_source_log.

Sheet Systems
A1: System | B1: Purpose | C1: Who uses it | D1: Data it holds | E1: Integration with other systems | F1: Source
A2: LOS — Loan Origination System | B2: Records each application and moves it between teams as a workflow queue | C2: Branch Sales Officer, Credit Operations Analyst, Underwriter, Disbursement Officer, Risk & Compliance Officer | D2: Application details, status, checks performed, credit decision, sanction terms | E2: Linked to DMS by application ID. Bureau report pulled through an interface. NOT integrated with CBS — loan terms re-keyed into CBS (manual bridge). KYC results typed in manually. | F2: S06, S07; integration is Assumption
A3: DMS — Document Management System | B3: Stores scanned documents for each application | C3: Branch Sales Officer (upload), Credit Operations Analyst, Underwriter, Risk & Compliance Officer | D3: Scanned KYC documents, income proofs, signed agreement, archived loan file | E3: Linked to LOS by application ID, but documents are tagged manually at scanning. No automatic reading of document content. | F3: S03, S05; Assumption
A4: CBS — Core Banking System | B4: Holds customer accounts; creates the loan account, releases funds and collects EMIs | C4: Disbursement Officer | D4: Customer accounts, loan account, disbursal and repayment records, mandate | E4: NOT integrated with LOS for loan creation — terms keyed in by the Disbursement Officer (manual bridge). Linked to mandate registration. | F4: S02, S04; integration is Assumption
A5: KYC / CKYC registry | B5: Central record of customers' verified KYC | C5: Credit Operations Analyst | D5: KYC identifier, identity and address details, photograph | E5: Accessed through a separate portal. Result recorded in the LOS by hand (manual bridge). | F5: S01
A6: Credit Bureau interface | B6: Returns the applicant's credit report and score | C6: Credit Operations Analyst; report read by Underwriter | D6: Credit score, existing loans and cards, repayment history | E6: Report pulled from the LOS and attached to the application (integrated). Obligation figures then copied into the underwriting spreadsheet (manual bridge). | F6: S06; Assumption
A8: Informal systems also used: email (H3, H7, H8, H10, H11) and spreadsheets (A15–A16). They hold process data outside the systems above, so their contents are invisible in the LOS.
